password_generator/__init__.py
password_generator/robust.py
robust_password_generator-0.0.3.dist-info/LICENSE.txt
robust_password_generator-0.0.3.dist-info/METADATA
robust_password_generator-0.0.3.dist-info/WHEEL
robust_password_generator-0.0.3.dist-info/top_level.txt
robust_password_generator-0.0.3.dist-info/RECORD
