Metadata-Version: 2.1
Name: robust-password-generator
Version: 0.0.3
Summary: Random Password Generator
Home-page: https://github.com/ravitejasravi/robust-password-generator
Author: Raviteja S
Author-email: <ravitejats18@gmail.com>
License: MIT
Keywords: python,password,strongpassword,security,random
Classifier: Development Status :: 4 - Beta
Classifier: Intended Audience :: Developers
Classifier: License :: OSI Approved :: MIT License
Classifier: Programming Language :: Python :: 3
Classifier: Operating System :: Unix
Classifier: Operating System :: MacOS :: MacOS X
Classifier: Operating System :: Microsoft :: Windows
License-File: LICENSE.txt
